<?xml version="1.0" encoding="utf-8"?><index PreMerged="False"><!-- saved from url=(0014)about:internet -->
<stem n="sale"><phr n="Sales"><ent r="1" t="3" w="116" /><ent r="1" t="6" w="332" /><ent r="1" t="13" w="73" /><ent r="1000" t="14" w="1" /><ent r="100" t="14" w="6" /><ent r="51" t="14" w="33" /><ent r="1" t="14" w="47" /><ent r="1000" t="15" w="1" /><ent r="100" t="15" w="6" /><ent r="51" t="15" w="36" /><ent r="51" t="15" w="40" /><ent r="1" t="15" w="51" /><ent r="51" t="17" w="41" /><ent r="51" t="17" w="45" /><ent r="51" t="17" w="133" /><ent r="51" t="18" w="30" /><ent r="51" t="18" w="34" /><ent r="1000" t="19" w="1" /><ent r="100" t="19" w="7" /><ent r="51" t="19" w="14" /><ent r="51" t="19" w="33" /><ent r="51" t="19" w="37" /><ent r="51" t="19" w="46" /><ent r="1" t="19" w="58" /><ent r="1" t="26" w="50" /><ent r="1" t="27" w="44" /><ent r="1" t="31" w="31" /><ent r="51" t="36" w="54" /><ent r="51" t="36" w="58" /><ent r="1000" t="39" w="3" /><ent r="51" t="39" w="10" /><ent r="51" t="39" w="27" /><ent r="1" t="39" w="37" /><ent r="1000" t="40" w="2" /><ent r="51" t="40" w="8" /><ent r="51" t="40" w="24" /><ent r="1" t="40" w="33" /><ent r="1" t="51" w="47" /><ent r="1" t="51" w="205" /><ent r="1" t="53" w="94" /><ent r="1" t="53" w="368" /><ent r="1" t="54" w="204" /><ent r="1" t="56" w="31" /><ent r="1" t="56" w="414" /><ent r="1" t="62" w="24" /><ent r="51" t="64" w="68" /><ent r="51" t="64" w="73" /><ent r="51" t="64" w="88" /><ent r="51" t="65" w="63" /><ent r="51" t="65" w="68" /><ent r="51" t="65" w="78" /><ent r="51" t="66" w="42" /><ent r="1" t="66" w="204" /><ent r="51" t="67" w="31" /><ent r="51" t="67" w="35" /><ent r="51" t="67" w="52" /><ent r="51" t="68" w="49" /><ent r="51" t="68" w="53" /><ent r="51" t="69" w="46" /><ent r="51" t="69" w="50" /><ent r="1000" t="70" w="6" /><ent r="100" t="70" w="14" /><ent r="51" t="70" w="23" /><ent r="51" t="70" w="43" /><ent r="51" t="70" w="47" /><ent r="1" t="72" w="76" /><ent r="140" t="72" w="100" /><ent r="51" t="72" w="390" /><ent r="51" t="77" w="30" /><ent r="51" t="77" w="34" /><ent r="51" t="77" w="55" /><ent r="51" t="77" w="154" /><ent r="51" t="78" w="42" /><ent r="1" t="81" w="187" /><ent r="51" t="82" w="31" /><ent r="51" t="82" w="35" /><ent r="51" t="82" w="56" /><ent r="51" t="83" w="43" /><ent r="1" t="84" w="40" /><ent r="1" t="90" w="295" /><ent r="1" t="95" w="41" /><ent r="1" t="95" w="162" /><ent r="1" t="95" w="192" /><ent r="1" t="103" w="29" /><ent r="1" t="104" w="50" /><ent r="1" t="105" w="206" /><ent r="1" t="108" w="27" /><ent r="1" t="109" w="51" /><ent r="1" t="114" w="359" /><ent r="51" t="115" w="58" /><ent r="51" t="115" w="63" /><ent r="51" t="115" w="73" /><ent r="1" t="116" w="87" /><ent r="51" t="117" w="24" /><ent r="51" t="117" w="28" /><ent r="51" t="117" w="37" /><ent r="51" t="117" w="54" /><ent r="1" t="117" w="132" /><ent r="51" t="119" w="31" /><ent r="51" t="119" w="35" /><ent r="51" t="119" w="52" /><ent r="51" t="121" w="28" /><ent r="51" t="121" w="32" /><ent r="51" t="123" w="28" /><ent r="51" t="123" w="32" /><ent r="51" t="123" w="298" /><ent r="1" t="124" w="58" /><ent r="1" t="126" w="156" /><ent r="51" t="127" w="30" /><ent r="51" t="127" w="34" /><ent r="51" t="127" w="55" /><ent r="1" t="127" w="180" /><ent r="51" t="128" w="34" /><ent r="51" t="128" w="38" /><ent r="51" t="130" w="24" /><ent r="51" t="130" w="28" /><ent r="51" t="130" w="37" /><ent r="51" t="130" w="57" /><ent r="51" t="130" w="181" /><ent r="1" t="131" w="126" /><ent r="51" t="132" w="31" /><ent r="51" t="132" w="35" /><ent r="51" t="134" w="28" /><ent r="51" t="134" w="32" /><ent r="1" t="135" w="155" /><ent r="51" t="136" w="30" /><ent r="51" t="136" w="34" /><ent r="51" t="136" w="121" /><ent r="1000" t="137" w="1" /><ent r="100" t="137" w="7" /><ent r="51" t="137" w="15" /><ent r="1" t="137" w="55" /><ent r="1" t="137" w="100" /><ent r="1" t="137" w="126" /><ent r="1000" t="138" w="1" /><ent r="100" t="138" w="6" /><ent r="51" t="138" w="12" /><ent r="51" t="138" w="34" /><ent r="1" t="138" w="48" /><ent r="51" t="138" w="101" /><ent r="1000" t="139" w="1" /><ent r="100" t="139" w="6" /><ent r="51" t="139" w="12" /><ent r="51" t="139" w="34" /><ent r="51" t="139" w="38" /><ent r="1" t="139" w="49" /><ent r="1000" t="140" w="1" /><ent r="100" t="140" w="6" /><ent r="51" t="140" w="10" /><ent r="1" t="140" w="15" /><ent r="51" t="140" w="63" /><ent r="51" t="140" w="68" /><ent r="51" t="140" w="83" /><ent r="1000" t="141" w="1" /><ent r="100" t="141" w="7" /><ent r="51" t="141" w="14" /><ent r="51" t="141" w="33" /><ent r="51" t="141" w="37" /><ent r="51" t="141" w="46" /><ent r="1" t="141" w="58" /><ent r="51" t="143" w="31" /><ent r="51" t="143" w="35" /><ent r="51" t="143" w="56" /><ent r="51" t="145" w="24" /><ent r="51" t="145" w="28" /><ent r="51" t="145" w="37" /><ent r="51" t="145" w="58" /><ent r="51" t="147" w="28" /><ent r="51" t="147" w="32" /></phr><phr n="sales"><ent r="1" t="4" w="111" /><ent r="1" t="14" w="447" /><ent r="1" t="28" w="44" /><ent r="1" t="29" w="48" /><ent r="1" t="30" w="46" /><ent r="1" t="39" w="43" /><ent r="1" t="39" w="65" /><ent r="1" t="56" w="399" /><ent r="1" t="61" w="358" /><ent r="1" t="67" w="265" /><ent r="51" t="70" w="69" /><ent r="1" t="74" w="82" /><ent r="1" t="77" w="144" /><ent r="1" t="81" w="192" /><ent r="1" t="90" w="304" /><ent r="1" t="90" w="310" /><ent r="1" t="92" w="246" /><ent r="1" t="95" w="47" /><ent r="1" t="96" w="87" /><ent r="1" t="116" w="93" /><ent r="1" t="126" w="167" /><ent r="1" t="127" w="190" /><ent r="1" t="135" w="160" /><ent r="1" t="140" w="37" /><ent r="1" t="142" w="96" /></phr><phr n="Sale"><ent r="1" t="11" w="280" /><ent r="1" t="11" w="294" /><ent r="1" t="11" w="311" /></phr><phr n="sale"><ent r="1" t="120" w="87" /></phr></stem><stem n="appli"><phr n="applies"><ent r="1" t="3" w="126" /><ent r="1" t="59" w="19" /><ent r="1" t="61" w="628" /></phr><phr n="apply"><ent r="1" t="10" w="191" /><ent r="1" t="11" w="59" /><ent r="1" t="11" w="213" /><ent r="1" t="11" w="226" /><ent r="1" t="116" w="96" /></phr><phr n="applied"><ent r="1" t="90" w="376" /></phr></stem><stem n="billabl"><phr n="Billable"><ent r="1" t="3" w="131" /><ent r="1" t="3" w="160" /><ent r="1" t="13" w="159" /><ent r="1" t="13" w="185" /><ent r="51" t="17" w="143" /><ent r="1" t="38" w="135" /><ent r="1" t="51" w="76" /><ent r="1" t="51" w="218" /><ent r="1000" t="65" w="1" /><ent r="100" t="65" w="6" /><ent r="51" t="65" w="10" /><ent r="1" t="65" w="15" /><ent r="1000" t="69" w="7" /><ent r="100" t="69" w="16" /><ent r="51" t="69" w="26" /><ent r="1" t="72" w="86" /><ent r="90" t="72" w="303" /><ent r="100" t="75" w="9" /><ent r="51" t="75" w="19" /><ent r="1" t="75" w="98" /><ent r="1" t="75" w="128" /><ent r="1" t="84" w="112" /><ent r="51" t="123" w="77" /><ent r="1" t="123" w="171" /><ent r="1" t="123" w="212" /><ent r="1" t="124" w="192" /><ent r="1" t="131" w="212" /><ent r="1" t="132" w="168" /><ent r="51" t="134" w="75" /><ent r="1" t="147" w="112" /></phr><phr n="billable"><ent r="1" t="65" w="37" /><ent r="51" t="69" w="76" /><ent r="1" t="74" w="72" /><ent r="1" t="75" w="32" /><ent r="1" t="80" w="117" /></phr></stem><stem n="rang"><phr n="range"><ent r="1" t="3" w="136" /><ent r="1" t="26" w="84" /><ent r="1" t="27" w="103" /><ent r="1" t="37" w="86" /><ent r="1" t="37" w="111" /><ent r="1" t="38" w="84" /><ent r="1" t="40" w="95" /><ent r="1" t="41" w="189" /><ent r="1" t="42" w="187" /><ent r="1" t="42" w="207" /><ent r="1" t="44" w="56" /><ent r="1" t="44" w="73" /><ent r="1" t="46" w="98" /><ent r="1" t="47" w="68" /><ent r="1" t="49" w="76" /></phr><phr n="ranges"><ent r="1" t="3" w="267" /><ent r="1" t="3" w="271" /><ent r="1" t="28" w="82" /><ent r="1" t="29" w="65" /><ent r="1" t="30" w="85" /><ent r="1" t="48" w="82" /></phr></stem><stem n="3"><phr n="3"><ent r="1" t="3" w="142" /><ent r="1" t="3" w="277" /><ent r="51" t="18" w="48" /><ent r="51" t="25" w="52" /><ent r="1" t="41" w="84" /><ent r="1" t="89" w="276" /><ent r="1" t="89" w="283" /><ent r="1" t="90" w="65" /><ent r="51" t="136" w="48" /></phr></stem><stem n="differ"><phr n="different"><ent r="1" t="3" w="149" /><ent r="1" t="6" w="396" /><ent r="1" t="33" w="108" /><ent r="1" t="34" w="179" /><ent r="1" t="47" w="83" /><ent r="1" t="53" w="340" /><ent r="1" t="56" w="319" /><ent r="1" t="58" w="90" /><ent r="1" t="58" w="92" /><ent r="1" t="69" w="172" /><ent r="1" t="70" w="304" /><ent r="1" t="84" w="22" /><ent r="1" t="88" w="63" /><ent r="1" t="94" w="80" /></phr><phr n="differ"><ent r="1" t="17" w="85" /></phr><phr n="difference"><ent r="1" t="109" w="149" /></phr></stem><stem n="sequenc"><phr n="sequence"><ent r="1" t="3" w="150" /><ent r="51" t="34" w="68" /><ent r="1" t="34" w="163" /><ent r="1" t="41" w="146" /><ent r="1" t="56" w="185" /><ent r="1" t="137" w="92" /></phr><phr n="Sequences"><ent r="1" t="3" w="255" /></phr><phr n="sequences"><ent r="1" t="34" w="196" /></phr><phr n="Sequence"><ent r="1" t="41" w="83" /><ent r="1" t="42" w="159" /><ent r="1" t="42" w="173" /></phr></stem><stem n="req"><phr n="Req"><ent r="1" t="3" w="172" /></phr></stem><stem n="req/whs"><phr n="Req/Whse"><ent r="1" t="3" w="173" /><ent r="1" t="3" w="172" /></phr></stem><stem n="whse"><phr n="Whse"><ent r="1" t="3" w="173" /><ent r="1" t="68" w="253" /><ent r="1" t="69" w="194" /><ent r="1" t="70" w="348" /></phr></stem><stem n="rel"><phr n="Rel"><ent r="1" t="3" w="174" /></phr></stem><stem n="field"><phr n="field"><ent r="1" t="3" w="175" /><ent r="1" t="10" w="176" /><ent r="1" t="11" w="147" /><ent r="1" t="11" w="154" /><ent r="1" t="14" w="96" /><ent r="1" t="14" w="127" /><ent r="1" t="16" w="64" /><ent r="1" t="16" w="72" /><ent r="1" t="22" w="102" /><ent r="1" t="22" w="133" /><ent r="1" t="25" w="104" /><ent r="1" t="26" w="234" /><ent r="1" t="26" w="253" /><ent r="1" t="27" w="180" /><ent r="1" t="27" w="199" /><ent r="1" t="28" w="166" /><ent r="51" t="29" w="132" /><ent r="51" t="29" w="144" /><ent r="51" t="30" w="169" /><ent r="51" t="30" w="188" /><ent r="1" t="33" w="131" /><ent r="1" t="34" w="71" /><ent r="1" t="37" w="101" /><ent r="1" t="39" w="142" /><ent r="1" t="46" w="77" /><ent r="1" t="51" w="102" /><ent r="1" t="51" w="121" /><ent r="1" t="51" w="145" /><ent r="1" t="51" w="183" /><ent r="1" t="52" w="271" /><ent r="1" t="52" w="292" /><ent r="1" t="56" w="224" /><ent r="1" t="56" w="411" /><ent r="1" t="58" w="135" /><ent r="1" t="58" w="187" /><ent r="1" t="59" w="211" /><ent r="1" t="60" w="32" /><ent r="1" t="60" w="50" /><ent r="1" t="60" w="86" /><ent r="1" t="60" w="328" /><ent r="1" t="60" w="340" /><ent r="1" t="61" w="363" /><ent r="1" t="66" w="100" /><ent r="1" t="68" w="433" /><ent r="1" t="69" w="303" /><ent r="1" t="70" w="174" /><ent r="1" t="72" w="126" /><ent r="1" t="73" w="89" /><ent r="1" t="77" w="115" /><ent r="1" t="77" w="134" /><ent r="1" t="77" w="158" /><ent r="1" t="77" w="167" /><ent r="1" t="77" w="215" /><ent r="1" t="77" w="249" /><ent r="1" t="79" w="135" /><ent r="1" t="88" w="73" /><ent r="1" t="88" w="115" /><ent r="1" t="89" w="160" /><ent r="1" t="89" w="219" /><ent r="1" t="90" w="74" /><ent r="1" t="90" w="126" /><ent r="1" t="90" w="178" /><ent r="1" t="90" w="222" /><ent r="1" t="90" w="254" /><ent r="1" t="90" w="270" /><ent r="1" t="90" w="357" /><ent r="1" t="90" w="409" /><ent r="1" t="90" w="501" /><ent r="1" t="91" w="64" /><ent r="1" t="91" w="69" /><ent r="1" t="91" w="206" /><ent r="1" t="95" w="107" /><ent r="1" t="95" w="200" /><ent r="1" t="97" w="27" /><ent r="1" t="98" w="69" /><ent r="1" t="101" w="29" /><ent r="1" t="102" w="73" /><ent r="1" t="102" w="85" /><ent r="1" t="104" w="143" /><ent r="1" t="104" w="229" /><ent r="1" t="109" w="71" /><ent r="1" t="109" w="81" /><ent r="1" t="109" w="96" /><ent r="1" t="109" w="108" /><ent r="1" t="109" w="159" /><ent r="1" t="109" w="178" /><ent r="1" t="117" w="84" /><ent r="1" t="117" w="134" /><ent r="1" t="117" w="151" /><ent r="1" t="120" w="24" /><ent r="1" t="122" w="186" /><ent r="1" t="123" w="166" /><ent r="1" t="123" w="195" /><ent r="1" t="123" w="207" /><ent r="1" t="123" w="228" /><ent r="1" t="123" w="250" /><ent r="1" t="126" w="116" /><ent r="1" t="126" w="189" /><ent r="1" t="126" w="215" /><ent r="1" t="126" w="292" /><ent r="1" t="127" w="131" /><ent r="1" t="127" w="147" /><ent r="1" t="127" w="183" /><ent r="1" t="127" w="204" /><ent r="1" t="129" w="162" /><ent r="1" t="131" w="64" /><ent r="1" t="131" w="115" /><ent r="1" t="132" w="99" /><ent r="1" t="132" w="113" /><ent r="1" t="134" w="133" /><ent r="1" t="134" w="183" /><ent r="1" t="134" w="243" /><ent r="1" t="134" w="270" /><ent r="1" t="138" w="97" /><ent r="1" t="138" w="126" /><ent r="1" t="149" w="136" /></phr><phr n="fields"><ent r="1" t="4" w="145" /><ent r="1" t="4" w="156" /><ent r="1" t="17" w="112" /><ent r="1" t="18" w="84" /><ent r="1" t="18" w="93" /><ent r="1" t="24" w="107" /><ent r="1" t="25" w="135" /><ent r="1" t="34" w="123" /><ent r="1" t="34" w="132" /><ent r="1" t="37" w="87" /><ent r="1" t="37" w="120" /><ent r="1" t="44" w="88" /><ent r="1" t="47" w="103" /><ent r="1" t="48" w="94" /><ent r="51" t="49" w="108" /><ent r="1" t="67" w="189" /><ent r="1" t="68" w="82" /><ent r="1" t="69" w="82" /><ent r="1" t="70" w="74" /><ent r="1" t="72" w="66" /><ent r="1" t="78" w="215" /><ent r="1" t="80" w="247" /><ent r="1" t="83" w="93" /><ent r="1" t="83" w="152" /><ent r="1" t="90" w="66" /><ent r="1" t="95" w="285" /><ent r="1" t="96" w="121" /><ent r="1" t="108" w="123" /><ent r="1" t="109" w="216" /><ent r="1" t="119" w="97" /><ent r="1" t="134" w="201" /><ent r="1" t="134" w="234" /><ent r="1" t="145" w="102" /><ent r="1" t="145" w="145" /><ent r="1" t="157" w="101" /></phr><phr n="Fields"><ent r="1000" t="81" w="5" /><ent r="100" t="81" w="11" /><ent r="51" t="81" w="19" /><ent r="1000" t="95" w="3" /><ent r="51" t="95" w="7" /><ent r="100" t="95" w="12" /><ent r="1000" t="97" w="4" /><ent r="100" t="97" w="9" /><ent r="51" t="97" w="15" /><ent r="1000" t="99" w="4" /><ent r="100" t="99" w="9" /><ent r="51" t="99" w="15" /><ent r="1000" t="101" w="5" /><ent r="100" t="101" w="11" /><ent r="51" t="101" w="17" /><ent r="1000" t="103" w="3" /><ent r="100" t="103" w="7" /><ent r="51" t="103" w="12" /><ent r="1000" t="105" w="5" /><ent r="100" t="105" w="11" /><ent r="51" t="105" w="18" /><ent r="1000" t="106" w="3" /><ent r="100" t="106" w="7" /><ent r="51" t="106" w="12" /><ent r="1000" t="108" w="3" /><ent r="100" t="108" w="7" /><ent r="51" t="108" w="12" /><ent r="1000" t="110" w="5" /><ent r="100" t="110" w="12" /><ent r="51" t="110" w="20" /><ent r="1000" t="112" w="6" /><ent r="100" t="112" w="14" /><ent r="51" t="112" w="23" /><ent r="1000" t="113" w="6" /><ent r="100" t="113" w="13" /><ent r="51" t="113" w="21" /><ent r="1000" t="114" w="4" /><ent r="51" t="114" w="10" /><ent r="1000" t="116" w="3" /><ent r="100" t="116" w="7" /><ent r="51" t="116" w="12" /><ent r="1000" t="118" w="4" /><ent r="100" t="118" w="9" /><ent r="51" t="118" w="15" /><ent r="1000" t="120" w="3" /><ent r="100" t="120" w="7" /><ent r="51" t="120" w="12" /><ent r="1000" t="122" w="3" /><ent r="100" t="122" w="7" /><ent r="51" t="122" w="12" /><ent r="1000" t="124" w="5" /><ent r="100" t="124" w="11" /><ent r="51" t="124" w="18" /><ent r="1000" t="126" w="4" /><ent r="100" t="126" w="9" /><ent r="51" t="126" w="14" /><ent r="1000" t="129" w="3" /><ent r="100" t="129" w="7" /><ent r="51" t="129" w="12" /><ent r="1000" t="131" w="4" /><ent r="100" t="131" w="9" /><ent r="51" t="131" w="15" /><ent r="1000" t="133" w="3" /><ent r="100" t="133" w="7" /><ent r="51" t="133" w="12" /><ent r="1000" t="135" w="5" /><ent r="100" t="135" w="11" /><ent r="51" t="135" w="19" /><ent r="1000" t="137" w="5" /><ent r="100" t="137" w="11" /><ent r="51" t="137" w="19" /><ent r="1000" t="142" w="4" /><ent r="100" t="142" w="9" /><ent r="51" t="142" w="15" /><ent r="1000" t="144" w="3" /><ent r="100" t="144" w="7" /><ent r="51" t="144" w="12" /><ent r="1000" t="146" w="3" /><ent r="100" t="146" w="7" /><ent r="51" t="146" w="12" /><ent r="1000" t="148" w="4" /><ent r="100" t="148" w="9" /><ent r="51" t="148" w="16" /><ent r="1000" t="150" w="3" /><ent r="100" t="150" w="7" /><ent r="51" t="150" w="14" /><ent r="1000" t="152" w="5" /><ent r="100" t="152" w="12" /><ent r="51" t="152" w="20" /><ent r="1000" t="153" w="5" /><ent r="100" t="153" w="11" /><ent r="51" t="153" w="19" /><ent r="1000" t="154" w="4" /><ent r="100" t="154" w="9" /><ent r="51" t="154" w="15" /><ent r="1000" t="155" w="5" /><ent r="100" t="155" w="11" /><ent r="51" t="155" w="18" /><ent r="1000" t="156" w="4" /><ent r="100" t="156" w="9" /><ent r="51" t="156" w="15" /></phr><phr n="Field"><ent r="1" t="81" w="22" /><ent r="1" t="95" w="14" /><ent r="1" t="97" w="18" /><ent r="1" t="99" w="18" /><ent r="1" t="101" w="20" /><ent r="1" t="103" w="15" /><ent r="1" t="105" w="21" /><ent r="1" t="106" w="15" /><ent r="1" t="108" w="15" /><ent r="1" t="110" w="23" /><ent r="1" t="112" w="26" /><ent r="1" t="113" w="24" /><ent r="1" t="114" w="13" /><ent r="1" t="116" w="15" /><ent r="1" t="118" w="18" /><ent r="1" t="120" w="15" /><ent r="1" t="122" w="15" /><ent r="1" t="124" w="21" /><ent r="1" t="126" w="17" /><ent r="1" t="129" w="15" /><ent r="1" t="131" w="18" /><ent r="1" t="133" w="15" /><ent r="1" t="135" w="22" /><ent r="1" t="137" w="22" /><ent r="1" t="142" w="18" /><ent r="1" t="144" w="15" /><ent r="1" t="146" w="15" /><ent r="1" t="148" w="19" /><ent r="1" t="150" w="17" /><ent r="1" t="152" w="23" /><ent r="1" t="153" w="22" /><ent r="1" t="154" w="18" /><ent r="1" t="155" w="21" /><ent r="1" t="156" w="18" /></phr></stem><stem n="address"><phr n="address"><ent r="1" t="3" w="180" /><ent r="1" t="3" w="204" /><ent r="1" t="3" w="210" /><ent r="1" t="3" w="234" /><ent r="1" t="5" w="85" /><ent r="1" t="19" w="65" /><ent r="1" t="52" w="48" /><ent r="1" t="58" w="86" /><ent r="1" t="66" w="52" /><ent r="1" t="66" w="236" /><ent r="1" t="78" w="51" /><ent r="1" t="81" w="43" /><ent r="1" t="81" w="53" /><ent r="1" t="81" w="60" /><ent r="1" t="81" w="74" /><ent r="1" t="83" w="100" /><ent r="1" t="116" w="44" /><ent r="1" t="117" w="64" /><ent r="1" t="117" w="112" /><ent r="1" t="118" w="76" /><ent r="1" t="129" w="87" /><ent r="1" t="130" w="126" /><ent r="1" t="135" w="55" /><ent r="1" t="141" w="65" /><ent r="1" t="144" w="84" /><ent r="1" t="145" w="111" /><ent r="1" t="156" w="64" /></phr><phr n="Address"><ent r="51" t="19" w="82" /><ent r="1" t="56" w="255" /><ent r="1000" t="66" w="1" /><ent r="100" t="66" w="4" /><ent r="51" t="66" w="8" /><ent r="51" t="66" w="27" /><ent r="1" t="66" w="37" /><ent r="1" t="78" w="57" /><ent r="51" t="78" w="266" /><ent r="1" t="81" w="71" /><ent r="1000" t="116" w="1" /><ent r="100" t="116" w="5" /><ent r="51" t="116" w="10" /><ent r="1" t="116" w="40" /><ent r="1000" t="117" w="1" /><ent r="100" t="117" w="4" /><ent r="51" t="117" w="8" /><ent r="1" t="117" w="49" /><ent r="1" t="117" w="115" /><ent r="1" t="118" w="71" /><ent r="1" t="135" w="52" /><ent r="51" t="141" w="82" /><ent r="1" t="144" w="76" /><ent r="1" t="156" w="59" /></phr><phr n="addresses"><ent r="1" t="26" w="153" /><ent r="1" t="58" w="69" /><ent r="1" t="58" w="93" /></phr><phr n="addressing"><ent r="1" t="50" w="11" /></phr></stem><stem n="phone"><phr n="phone"><ent r="1" t="3" w="182" /><ent r="1" t="118" w="106" /></phr><phr n="Phone"><ent r="1" t="118" w="101" /></phr></stem><stem n="proof"><phr n="proofs"><ent r="1" t="3" w="185" /><ent r="1" t="3" w="194" /></phr><phr n="Proof"><ent r="1" t="81" w="288" /><ent r="1" t="135" w="231" /><ent r="1" t="150" w="105" /><ent r="1" t="150" w="114" /><ent r="1" t="151" w="137" /></phr><phr n="proof"><ent r="1" t="81" w="298" /><ent r="1" t="135" w="238" /><ent r="1" t="150" w="112" /><ent r="1" t="150" w="123" /><ent r="1" t="151" w="65" /></phr></stem><stem n="sent"><phr n="sent"><ent r="1" t="3" w="189" /><ent r="1" t="3" w="201" /><ent r="1" t="3" w="241" /><ent r="1" t="52" w="39" /><ent r="1" t="52" w="85" /><ent r="1" t="78" w="165" /><ent r="1" t="78" w="177" /></phr></stem><stem n="offic"><phr n="office"><ent r="1" t="3" w="209" /><ent r="1" t="57" w="137" /></phr><phr n="Office"><ent r="1" t="70" w="220" /><ent r="1" t="83" w="129" /></phr></stem><stem n="last"><phr n="last"><ent r="1" t="3" w="223" /><ent r="1" t="41" w="47" /><ent r="1" t="42" w="66" /><ent r="1" t="51" w="250" /><ent r="1" t="51" w="260" /><ent r="1" t="51" w="274" /><ent r="1" t="91" w="80" /><ent r="1" t="92" w="188" /><ent r="1" t="94" w="264" /><ent r="1" t="94" w="267" /><ent r="1" t="94" w="270" /><ent r="1" t="94" w="276" /><ent r="1" t="94" w="283" /><ent r="1" t="94" w="340" /></phr><phr n="LAST"><ent r="1" t="26" w="95" /><ent r="1" t="27" w="114" /><ent r="1" t="28" w="93" /><ent r="1" t="29" w="75" /><ent r="1" t="30" w="95" /><ent r="1" t="49" w="91" /></phr><phr n="Last"><ent r="1" t="89" w="114" /><ent r="1" t="92" w="176" /><ent r="1" t="92" w="181" /></phr></stem><stem n="three"><phr n="three"><ent r="1" t="3" w="224" /><ent r="1" t="30" w="106" /><ent r="1" t="47" w="82" /><ent r="1" t="93" w="118" /></phr></stem><stem n="digit"><phr n="digits"><ent r="1" t="3" w="225" /></phr></stem><stem n="should"><phr n="should"><ent r="1" t="3" w="239" /><ent r="1" t="10" w="144" /><ent r="1" t="11" w="182" /><ent r="1" t="11" w="201" /><ent r="1" t="11" w="212" /><ent r="1" t="11" w="232" /><ent r="1" t="20" w="115" /><ent r="1" t="51" w="333" /><ent r="1" t="53" w="168" /><ent r="1" t="53" w="261" /><ent r="1" t="54" w="95" /><ent r="1" t="57" w="163" /><ent r="1" t="61" w="210" /><ent r="1" t="68" w="268" /><ent r="1" t="69" w="199" /><ent r="1" t="70" w="363" /><ent r="1" t="72" w="273" /><ent r="1" t="72" w="276" /><ent r="1" t="77" w="243" /><ent r="1" t="78" w="202" /><ent r="1" t="79" w="119" /><ent r="1" t="89" w="419" /><ent r="1" t="105" w="469" /><ent r="1" t="108" w="103" /><ent r="1" t="114" w="144" /><ent r="1" t="114" w="318" /><ent r="1" t="114" w="355" /><ent r="1" t="114" w="364" /><ent r="1" t="124" w="98" /><ent r="1" t="124" w="163" /></phr></stem><stem n="nine"><phr n="nine"><ent r="1" t="3" w="252" /><ent r="1" t="57" w="111" /><ent r="1" t="61" w="76" /></phr></stem><stem n="altern"><phr n="Alternate"><ent r="1" t="3" w="253" /><ent r="1000" t="88" w="6" /><ent r="51" t="88" w="16" /><ent r="1" t="88" w="237" /><ent r="51" t="89" w="431" /><ent r="51" t="92" w="129" /></phr><phr n="alternate"><ent r="1" t="58" w="149" /><ent r="1" t="88" w="43" /><ent r="1" t="88" w="247" /><ent r="1" t="88" w="277" /><ent r="1" t="88" w="306" /><ent r="1" t="92" w="142" /><ent r="1" t="92" w="144" /><ent r="1" t="137" w="89" /></phr><phr n="alternates"><ent r="1" t="88" w="294" /></phr></stem><stem n="addit"><phr n="additional"><ent r="1" t="3" w="264" /><ent r="1" t="13" w="177" /><ent r="1" t="13" w="214" /><ent r="1" t="25" w="124" /><ent r="1" t="27" w="71" /><ent r="1" t="29" w="86" /><ent r="1" t="34" w="122" /><ent r="1" t="37" w="127" /><ent r="1" t="37" w="130" /><ent r="1" t="47" w="102" /><ent r="1" t="48" w="93" /><ent r="1" t="51" w="192" /><ent r="1" t="53" w="415" /><ent r="1" t="54" w="70" /><ent r="1" t="56" w="398" /><ent r="1" t="61" w="809" /><ent r="1" t="67" w="188" /><ent r="1" t="67" w="257" /><ent r="1" t="68" w="160" /><ent r="1" t="68" w="543" /><ent r="1" t="69" w="421" /><ent r="1" t="70" w="149" /><ent r="1" t="70" w="647" /><ent r="1" t="78" w="214" /><ent r="1" t="78" w="296" /><ent r="1" t="79" w="212" /><ent r="1" t="83" w="51" /><ent r="1" t="90" w="505" /><ent r="1" t="109" w="367" /><ent r="1" t="114" w="174" /><ent r="1" t="114" w="198" /><ent r="1" t="114" w="324" /><ent r="1" t="145" w="98" /></phr><phr n="Additional"><ent r="1" t="61" w="212" /><ent r="1" t="61" w="785" /></phr><phr n="addition"><ent r="1" t="88" w="330" /></phr></stem><stem n="outsid"><phr n="outside"><ent r="1" t="3" w="268" /><ent r="1" t="13" w="84" /></phr></stem><stem n="2"><phr n="2"><ent r="1" t="3" w="275" /><ent r="51" t="16" w="41" /><ent r="51" t="17" w="55" /><ent r="51" t="24" w="54" /><ent r="1" t="26" w="224" /><ent r="1" t="27" w="170" /><ent r="51" t="30" w="159" /><ent r="1" t="37" w="115" /><ent r="1" t="42" w="174" /><ent r="51" t="68" w="63" /><ent r="51" t="69" w="60" /><ent r="51" t="70" w="57" /><ent r="51" t="71" w="33" /><ent r="51" t="72" w="32" /><ent r="1" t="73" w="32" /><ent r="51" t="79" w="36" /><ent r="51" t="80" w="32" /><ent r="51" t="85" w="32" /><ent r="1" t="95" w="89" /><ent r="51" t="121" w="45" /><ent r="51" t="123" w="42" /><ent r="51" t="128" w="48" /><ent r="51" t="132" w="49" /><ent r="51" t="134" w="45" /><ent r="51" t="147" w="45" /></phr></stem><stem n="s3"><phr n="S3"><ent r="51" t="4" w="25" /><ent r="1" t="57" w="179" /><ent r="1" t="60" w="352" /><ent r="51" t="96" w="23" /></phr></stem><stem n="control"><phr n="Control"><ent r="51" t="4" w="33" /><ent r="1" t="60" w="377" /></phr><phr n="controlling"><ent r="51" t="29" w="137" /></phr><phr n="control"><ent r="1" t="40" w="121" /><ent r="1" t="44" w="93" /><ent r="1" t="46" w="79" /><ent r="1" t="72" w="345" /><ent r="1" t="93" w="128" /></phr><phr n="controlled"><ent r="1" t="142" w="88" /><ent r="1" t="142" w="119" /></phr></stem><stem n="ic"><phr n="ICS"><ent r="51" t="4" w="44" /></phr></stem><stem n="broad"><phr n="broad"><ent r="1" t="4" w="59" /><ent r="1" t="96" w="34" /></phr></stem><stem n="categor"><phr n="categorizing"><ent r="1" t="4" w="63" /><ent r="1" t="96" w="38" /></phr></stem><stem n="descript"><phr n="description"><ent r="1" t="4" w="102" /><ent r="1" t="7" w="97" /><ent r="1" t="8" w="104" /><ent r="1" t="9" w="87" /><ent r="1" t="10" w="93" /><ent r="1" t="11" w="118" /><ent r="1" t="61" w="96" /><ent r="1" t="61" w="209" /><ent r="1" t="61" w="783" /><ent r="1" t="71" w="363" /><ent r="1" t="95" w="34" /><ent r="1" t="96" w="78" /><ent r="1" t="152" w="96" /></phr><phr n="Description"><ent r="1" t="24" w="102" /><ent r="1" t="81" w="24" /><ent r="1" t="95" w="16" /><ent r="1" t="95" w="31" /><ent r="1" t="97" w="20" /><ent r="1" t="99" w="20" /><ent r="1" t="101" w="22" /><ent r="1" t="103" w="17" /><ent r="1" t="105" w="23" /><ent r="1" t="106" w="17" /><ent r="1" t="108" w="17" /><ent r="1" t="110" w="25" /><ent r="1" t="112" w="28" /><ent r="1" t="113" w="26" /><ent r="1" t="114" w="15" /><ent r="1" t="116" w="17" /><ent r="1" t="118" w="20" /><ent r="1" t="120" w="17" /><ent r="1" t="122" w="17" /><ent r="1" t="124" w="23" /><ent r="1" t="126" w="19" /><ent r="1" t="129" w="17" /><ent r="1" t="131" w="20" /><ent r="1" t="133" w="17" /><ent r="1" t="135" w="24" /><ent r="1" t="137" w="24" /><ent r="1" t="142" w="20" /><ent r="1" t="144" w="17" /><ent r="1" t="146" w="17" /><ent r="1" t="148" w="21" /><ent r="1" t="150" w="19" /><ent r="1" t="152" w="25" /><ent r="1" t="152" w="93" /><ent r="1" t="153" w="24" /><ent r="1" t="154" w="20" /><ent r="1" t="155" w="23" /><ent r="1" t="156" w="20" /></phr></stem><stem n="distribut"><phr n="distribution"><ent r="1" t="4" w="112" /><ent r="1" t="95" w="48" /><ent r="1" t="96" w="88" /></phr><phr n="distributed"><ent r="1" t="51" w="357" /></phr><phr n="distributing"><ent r="1" t="91" w="193" /></phr></stem><stem n="g"><phr n="G"><ent r="1" t="4" w="121" /><ent r="1" t="61" w="475" /><ent r="1" t="95" w="60" /><ent r="1" t="96" w="97" /></phr></stem><stem n="g/l"><phr n="G/L"><ent r="1" t="4" w="122" /><ent r="1" t="4" w="121" /><ent r="1" t="61" w="476" /><ent r="1" t="61" w="475" /><ent r="1" t="95" w="61" /><ent r="1" t="95" w="60" /><ent r="1" t="96" w="98" /><ent r="1" t="96" w="97" /></phr></stem><stem n="l"><phr n="L"><ent r="1" t="4" w="122" /><ent r="1" t="61" w="476" /><ent r="1" t="95" w="61" /><ent r="1" t="96" w="98" /></phr></stem><stem n="account"><phr n="accounts"><ent r="1" t="4" w="123" /><ent r="1" t="95" w="62" /><ent r="1" t="96" w="99" /><ent r="1" t="120" w="82" /></phr><phr n="accounted"><ent r="1" t="34" w="203" /></phr><phr n="Accounting"><ent r="1" t="59" w="429" /><ent r="1" t="59" w="453" /><ent r="1" t="103" w="82" /></phr><phr n="Accounts"><ent r="1" t="60" w="73" /><ent r="1" t="60" w="268" /><ent r="1" t="142" w="91" /></phr><phr n="Account"><ent r="1" t="61" w="222" /><ent r="1" t="83" w="150" /><ent r="1" t="144" w="113" /><ent r="1" t="144" w="118" /><ent r="1" t="144" w="121" /><ent r="1" t="144" w="125" /><ent r="1" t="145" w="140" /><ent r="1" t="145" w="143" /></phr><phr n="account"><ent r="1" t="61" w="447" /><ent r="1" t="61" w="458" /><ent r="1" t="61" w="477" /><ent r="1" t="83" w="115" /></phr><phr n="accounting"><ent r="1" t="103" w="87" /><ent r="1" t="103" w="104" /><ent r="1" t="103" w="128" /><ent r="51" t="104" w="195" /><ent r="1" t="105" w="455" /></phr></stem><stem n="write"><phr n="write"><ent r="1" t="4" w="130" /><ent r="1" t="61" w="640" /><ent r="1" t="96" w="106" /></phr></stem><stem n="tax"><phr n="tax"><ent r="1" t="4" w="136" /><ent r="1" t="66" w="238" /><ent r="1" t="67" w="266" /><ent r="1" t="80" w="310" /><ent r="1" t="89" w="158" /><ent r="1" t="95" w="80" /><ent r="1" t="96" w="112" /><ent r="1" t="116" w="94" /><ent r="1" t="118" w="65" /></phr><phr n="Tax"><ent r="1" t="95" w="73" /><ent r="1" t="95" w="86" /><ent r="1" t="116" w="88" /><ent r="1" t="117" w="133" /></phr></stem></index>